shellypython/__init__.py
shellypython/const.py
shellypython/exception.py
shellypython/helpers.py
shellypython/shelly.py
shellypython/test2.py
shellypython-0.1.1.dist-info/LICENSE
shellypython-0.1.1.dist-info/METADATA
shellypython-0.1.1.dist-info/WHEEL
shellypython-0.1.1.dist-info/top_level.txt
shellypython-0.1.1.dist-info/RECORD
