Metadata-Version: 2.1
Name: shellypython
Version: 0.1.1
Summary: Python interface for Shelly.cloud devices.
Home-page: https://github.com/marcogazzola/shelly-python
Author: Marco Gazzola
License: UNKNOWN
Download-URL: https://github.com/marcogazzola/shelly-python/tarball/0.1.1
Keywords: shelly,shelly-cloud,rele,api,mqtt
Platform: UNKNOWN
Classifier: Intended Audience :: Developers
Classifier: License :: OSI Approved :: MIT License
Classifier: Operating System :: OS Independent
Classifier: Programming Language :: Python :: 3
Classifier: Programming Language :: Python :: 3.5
Classifier: Programming Language :: Python :: 3.6
Classifier: Programming Language :: Python :: 3.7
Classifier: Programming Language :: Python
Classifier: Topic :: Software Development :: Libraries :: Python Modules
Requires-Dist: requests (>=2.20.0)
